setup.py
sator/__init__.py
sator/const.py
sator/core.py
sator/pcset.py
sator/pset.py
sator/runtests.py
sator/setbase.py
sator/setrowbase.py
sator/sim.py
sator/tonerow.py
sator/utils.py
sator.egg-info/PKG-INFO
sator.egg-info/SOURCES.txt
sator.egg-info/dependency_links.txt
sator.egg-info/top_level.txt
sator.egg-info/zip-safe
sator/test/__init__.py
sator/test/neo_r.py
sator/test/pset_basic.py
sator/test/pset_oper.py
sator/test/pset_prime.py
sator/test/sim_mzc.py
sator/test/tonerow.py