Metadata-Version: 1.0
Name: sator
Version: 0.2
Summary: Sator is a python module for atonal music theory analysis.
Home-page: https://github.com/calebsmith/Sator
Author: Caleb Smith
Author-email: caleb.smithnc@gmail.com
License: GPL
Platform: UNKNOWN
Classifier: Topic :: Other/Nonlisted Topic
Classifier: Intended Audience :: Developers
Classifier: License :: OSI Approved :: GNU General Public License (GPL)
Classifier: Programming Language :: Python
Classifier: Topic :: Software Development :: Libraries :: Python Modules
Classifier: Development Status :: 4 - Beta
Classifier: Operating System :: OS Independent
